powertrace/__init__.py
powertrace/py.typed
powertrace/context/__init__.py
powertrace/context/config.py
powertrace/context/context.py
powertrace/main/__init__.py
powertrace/main/main.py
powertrace/models/__init__.py
powertrace/models/path.py
powertrace/models/traceback.py
powertrace/notebook/__init__.py
powertrace/notebook/extension.py
powertrace/notebook/rich_monkeypatch.py
powertrace/powertrace/__init__.py
powertrace/powertrace/install.py
powertrace/powertrace/powertrace.py
powertrace/powertrace/traceback.py
powertrace/powertrace/visualize.py
powertrace/powertrace/visualizer.py
powertrace-0.1.6.dist-info/licenses/LICENSE
powertrace-0.1.6.dist-info/METADATA
powertrace-0.1.6.dist-info/WHEEL
powertrace-0.1.6.dist-info/top_level.txt
powertrace-0.1.6.dist-info/RECORD
