Metadata-Version: 2.4
Name: powertrace
Version: 0.1.6
Summary: Detailed stack trace logging and visualization
Author-email: Quinten Roets <qdr2104@columbia.edu>
License-Expression: MIT
Project-URL: Source Code, https://github.com/quintenroets/powertrace
Requires-Python: <3.14,>=3.10
License-File: LICENSE
Requires-Dist: package-utils[context]<1,>=0.6.6
Requires-Dist: powercli<1,>=0.3.7
Requires-Dist: rich<15,>=13.7.1
Requires-Dist: superpathlib<3,>=2.0.4
Provides-Extra: dev
Requires-Dist: package-dev-tools<1,>=0.7.1; extra == "dev"
Requires-Dist: package-dev-utils<1,>=0.1.6; extra == "dev"
Requires-Dist: pexpect<5,>=4.9.0; extra == "dev"
Dynamic: license-file
